makefile_to_markdown/__init__.py
makefile_to_markdown/cli.py
makefile_to_markdown/core.py
makefile_to_markdown-0.1.1.dist-info/AUTHORS.md
makefile_to_markdown-0.1.1.dist-info/LICENSE
makefile_to_markdown-0.1.1.dist-info/METADATA
makefile_to_markdown-0.1.1.dist-info/WHEEL
makefile_to_markdown-0.1.1.dist-info/entry_points.txt
makefile_to_markdown-0.1.1.dist-info/top_level.txt
makefile_to_markdown-0.1.1.dist-info/RECORD
