Metadata-Version: 2.1
Name: makefile-to-markdown
Version: 0.1.1
Summary: Simple command-line utility that converts Makefiles to Markdown if specific commenting style is followed.
Author-email: Tim Santor <tsantor@xstudios.com>
Project-URL: Repository, https://github.com/tsantor/makefile-to-markdown.git
Project-URL: Issues, https://github.com/tsantor/makefile-to-markdown/issues
Project-URL: Changelog, https://github.com/tsantor/makefile-to-markdown/blob/master/HISTORY.md
Classifier: Development Status :: 5 - Production/Stable
Classifier: Environment :: Console
Classifier: Intended Audience :: Developers
Classifier: Natural Language :: English
Classifier: Programming Language :: Python :: 3.8
Classifier: Programming Language :: Python :: 3.9
Classifier: Programming Language :: Python :: 3.10
Classifier: Programming Language :: Python :: 3.11
Classifier: Programming Language :: Python :: 3.12
Requires-Python: >=3.8
License-File: LICENSE
License-File: AUTHORS.md
Requires-Dist: click
Provides-Extra: dev
